mux2_1/mux2_1.v
module mux2_1(
input a,
input b,
input s0,
output y);

assign y = s0 ? b : a;
endmodule

Dff/Dff.v
module dff(d, clk, q, qbar);
    input wire d, clk;
    output reg q, qbar;

    always@(posedge clk) begin
        q <= d;
        qbar <= ~d;
    end
endmodule

register_4b/register_4b.v
module register_4b (clk, load, data_in, data_out);
    input wire clk, load;
    input wire [3:0] data_in;
    output wire [3:0] data_out;

wire m0, m1, m2, m3;

dff dff0 (.d(m0), .clk(clk), .q(data_out[0]), .qbar());
dff dff1 (.d(m1), .clk(clk), .q(data_out[1]), .qbar());
dff dff2 (.d(m2), .clk(clk), .q(data_out[2]), .qbar());
dff dff3 (.d(m3), .clk(clk), .q(data_out[3]), .qbar());

mux2_1 mux0 (.a(data_out[0]), .b(data_in[0]), .s0(load), .y(m0));
mux2_1 mux1 (.a(data_out[1]), .b(data_in[1]), .s0(load), .y(m1));
mux2_1 mux2 (.a(data_out[2]), .b(data_in[2]), .s0(load), .y(m2));
mux2_1 mux3 (.a(data_out[3]), .b(data_in[3]), .s0(load), .y(m3));

endmodule

register_4b/register_4b_tb.v
`timescale 1ns/1ps

module register_4b_tb;

    // Inputs
    reg clk;
    reg load;
    reg [3:0] data_in;

    // Output
    wire [3:0] data_out;

    // Instantiate register
    register_4b uut (
        .clk(clk),
        .load(load),
        .data_in(data_in),
        .data_out(data_out)
    );

    // Clock generation
    always #5 clk = ~clk;

    initial begin

        // Waveform generation
        $dumpfile("register_4b_tb.vcd");
        $dumpvars(0, register_4b_tb);

        // Monitor
        $monitor("Time=%0t | clk=%b load=%b data_in=%b | data_out=%b",
                 $time, clk, load, data_in, data_out);

        // Initial values
        clk = 0;
        load = 0;
        data_in = 4'b0000;

        // -------------------------
        // Test 1: Load 1010
        // -------------------------
        #2;
        load = 1;
        data_in = 4'b1010;

        // Wait for clock edge
        #10;

        // -------------------------
        // Test 2: Load 1100
        // -------------------------
        data_in = 4'b1100;

        #10;

        // -------------------------
        // Test 3: Hold 1100
        // -------------------------
        load = 0;
        data_in = 4'b0011;

        #10;

        // -------------------------
        // Test 4: Hold again
        // -------------------------
        data_in = 4'b1111;

        #10;

        // -------------------------
        // Test 5: Load 0110
        // -------------------------
        load = 1;
        data_in = 4'b0110;

        #10;

        // -------------------------
        // Test 6: Hold 0110
        // -------------------------
        load = 0;
        data_in = 4'b1001;

        #10;

        $finish;

    end

endmodule

register_4b/register_4b_tb.vcd
$date
	Tue Sep 29 08:15:42 2026
$end
$version
	Icarus Verilog
$end
$timescale
	1ps
$end
$scope module register_4b_tb $end
$var wire 4 ! data_out [3:0] $end
$var reg 1 " clk $end
$var reg 4 # data_in [3:0] $end
$var reg 1 $ load $end
$scope module uut $end
$var wire 1 " clk $end
$var wire 4 % data_in [3:0] $end
$var wire 1 $ load $end
$var wire 1 & m3 $end
$var wire 1 ' m2 $end
$var wire 1 ( m1 $end
$var wire 1 ) m0 $end
$var wire 4 * data_out [3:0] $end
$scope module dff0 $end
$var wire 1 " clk $end
$var wire 1 ) d $end
$var reg 1 + q $end
$var reg 1 , qbar $end
$upscope $end
$scope module dff1 $end
$var wire 1 " clk $end
$var wire 1 ( d $end
$var reg 1 - q $end
$var reg 1 . qbar $end
$upscope $end
$scope module dff2 $end
$var wire 1 " clk $end
$var wire 1 ' d $end
$var reg 1 / q $end
$var reg 1 0 qbar $end
$upscope $end
$scope module dff3 $end
$var wire 1 " clk $end
$var wire 1 & d $end
$var reg 1 1 q $end
$var reg 1 2 qbar $end
$upscope $end
$scope module mux0 $end
$var wire 1 3 a $end
$var wire 1 4 b $end
$var wire 1 $ s0 $end
$var wire 1 ) y $end
$upscope $end
$scope module mux1 $end
$var wire 1 5 a $end
$var wire 1 6 b $end
$var wire 1 $ s0 $end
$var wire 1 ( y $end
$upscope $end
$scope module mux2 $end
$var wire 1 7 a $end
$var wire 1 8 b $end
$var wire 1 $ s0 $end
$var wire 1 ' y $end
$upscope $end
$scope module mux3 $end
$var wire 1 9 a $end
$var wire 1 : b $end
$var wire 1 $ s0 $end
$var wire 1 & y $end
$upscope $end
$upscope $end
$upscope $end
$enddefinitions $end
#0
$dumpvars
0:
x9
08
x7
06
x5
04
x3
x2
x1
x0
x/
x.
x-
x,
x+
bx *
x)
x(
x'
x&
b0 %
0$
b0 #
0"
bx !
$end
#2000
16
1:
0)
1(
0'
1&
b1010 #
b1010 %
1$
#5000
03
15
07
19
1,
0+
0.
1-
10
0/
02
b1010 !
b1010 *
11
1"
#10000
0"
#12000
0(
1'
06
18
b1100 #
b1100 %
#15000
17
05
00
1/
1.
b1100 !
b1100 *
0-
1"
#20000
0"
#22000
14
16
08
0:
b11 #
b11 %
0$
#25000
1"
#30000
0"
#32000
18
1:
b1111 #
b1111 %
#35000
1"
#40000
0"
#42000
0&
04
0:
0)
1(
b110 #
b110 %
1$
#45000
15
09
0.
1-
12
b110 !
b110 *
01
1"
#50000
0"
#52000
14
06
08
1:
b1001 #
b1001 %
0$
