not_gate/not_gate.v
module not_gate(
 input a,
 output y);

assign y = ~ a;
endmodule

not_gate/not_gate_tb.v
`timescale 1ns/1ps

module not_gate_tb;

    // Testbench signals
    reg a;
    wire y;

    // Instantiate the DUT
    not_gate uut (
        .a(a),
        .y(y)
    );

    // Generate VCD file for GTKWave
    initial begin
        $dumpfile("not_gate.vcd");
        $dumpvars(0, not_gate_tb);
    end

    // Display values in terminal
    initial begin
        $display("Time(ns)\ta\ty");
        $monitor("%0t\t%b\t%b", $time, a, y);
    end

    // Toggle input every 10 ns for 200 ns
    initial begin
        a = 0;

        repeat (20) begin
            #10 a = ~a;
        end

        #10 $finish;
    end

endmodule

not_gate/not_gate.vcd
$date
	Mon Aug  3 04:54:18 2026
$end
$version
	Icarus Verilog
$end
$timescale
	1ps
$end
$scope module not_gate_tb $end
$var wire 1 ! y $end
$var reg 1 " a $end
$scope module uut $end
$var wire 1 " a $end
$var wire 1 ! y $end
$upscope $end
$upscope $end
$enddefinitions $end
#0
$dumpvars
0"
1!
$end
#10000
0!
1"
#20000
1!
0"
#30000
0!
1"
#40000
1!
0"
#50000
0!
1"
#60000
1!
0"
#70000
0!
1"
#80000
1!
0"
#90000
0!
1"
#100000
1!
0"
#110000
0!
1"
#120000
1!
0"
#130000
0!
1"
#140000
1!
0"
#150000
0!
1"
#160000
1!
0"
#170000
0!
1"
#180000
1!
0"
#190000
0!
1"
#200000
1!
0"
