comparater_1b/comp1b.v
module comp1b (a, b, y);
    input wire a;
    input wire b;
    output wire [2:0] y;
    
    assign y[2] = (a & ~b);
    assign y[1] = ~(a ^ b);
    assign y[0] = (~a & b); 
endmodule

comparater_4b/comp4b.v
module comp4b (a, b, G, E, L);
    input wire [3:0] a;
    input wire [3:0] b;
    output wire G;
    output wire E;
    output wire L;
wire [2:0] y1, y2, y3, y4;
    
    comp1b c1 (a[0], b[0], y1);
    comp1b c2 (a[1], b[1], y2);
    comp1b c3 (a[2], b[2], y3);
    comp1b c4 (a[3], b[3], y4);
    
    assign G = y4[2] |
           (y4[1] & y3[2]) |
           (y4[1] & y3[1] & y2[2]) |
           (y4[1] & y3[1] & y2[1] & y1[2]);

    assign E = y4[1] & y3[1] & y2[1] & y1[1];
    assign L = y4[0] |
           (y4[1] & y3[0]) |
           (y4[1] & y3[1] & y2[0]) |
           (y4[1] & y3[1] & y2[1] & y1[0]);
endmodule

comparater_4b/comp4b_tb.v
`timescale 1ns/1ps

module comp4b_tb;

    reg [3:0] a;
    reg [3:0] b;

    wire G;
    wire E;
    wire L;

    integer i;
    integer j;

    comp4b uut (
        .a(a),
        .b(b),
        .G(G),
        .E(E),
        .L(L)
    );

    initial begin

        $dumpfile("comp4b_tb.vcd");
        $dumpvars(0, comp4b_tb);

        $display("-----------------------------------------");
        $display("   A     B   | G  E  L | Result");
        $display("-----------------------------------------");

        for (i = 0; i < 16; i = i + 1) begin

            for (j = 0; j < 16; j = j + 1) begin

                a = i;
                b = j;

                #10;

                if ((i > j) && (G == 1 && E == 0 && L == 0))
                    $display("  %04b  %04b | %b  %b  %b | PASS", a, b, G, E, L);

                else if ((i == j) && (G == 0 && E == 1 && L == 0))
                    $display("  %04b  %04b | %b  %b  %b | PASS", a, b, G, E, L);

                else if ((i < j) && (G == 0 && E == 0 && L == 1))
                    $display("  %04b  %04b | %b  %b  %b | PASS", a, b, G, E, L);

                else
                    $display("  %04b  %04b | %b  %b  %b | FAIL", a, b, G, E, L);

            end
        end

        $display("-----------------------------------------");
        $finish;

    end

endmodule

comparater_4b/comp4b_tb.vcd
$date
	Sun Sep 27 13:50:56 2026
$end
$version
	Icarus Verilog
$end
$timescale
	1ps
$end
$scope module comp4b_tb $end
$var wire 1 ! L $end
$var wire 1 " G $end
$var wire 1 # E $end
$var reg 4 $ a [3:0] $end
$var reg 4 % b [3:0] $end
$var integer 32 & i [31:0] $end
$var integer 32 ' j [31:0] $end
$scope module uut $end
$var wire 1 # E $end
$var wire 1 " G $end
$var wire 1 ! L $end
$var wire 4 ( a [3:0] $end
$var wire 4 ) b [3:0] $end
$var wire 3 * y4 [2:0] $end
$var wire 3 + y3 [2:0] $end
$var wire 3 , y2 [2:0] $end
$var wire 3 - y1 [2:0] $end
$scope module c1 $end
$var wire 1 . a $end
$var wire 1 / b $end
$var wire 3 0 y [2:0] $end
$upscope $end
$scope module c2 $end
$var wire 1 1 a $end
$var wire 1 2 b $end
$var wire 3 3 y [2:0] $end
$upscope $end
$scope module c3 $end
$var wire 1 4 a $end
$var wire 1 5 b $end
$var wire 3 6 y [2:0] $end
$upscope $end
$scope module c4 $end
$var wire 1 7 a $end
$var wire 1 8 b $end
$var wire 3 9 y [2:0] $end
$upscope $end
$upscope $end
$upscope $end
$enddefinitions $end
#0
$dumpvars
b10 9
08
07
b10 6
05
04
b10 3
02
01
b10 0
0/
0.
b10 -
b10 ,
b10 +
b10 *
b0 )
b0 (
b0 '
b0 &
b0 %
b0 $
1#
0"
0!
$end
#10000
0#
1!
b1 -
b1 0
1/
b1 %
b1 )
b1 '
#20000
b10 -
b10 0
b1 ,
b1 3
0/
12
b10 %
b10 )
b10 '
#30000
b1 -
b1 0
1/
b11 %
b11 )
b11 '
#40000
b10 -
b10 0
b10 ,
b10 3
b1 +
b1 6
0/
02
15
b100 %
b100 )
b100 '
#50000
b1 -
b1 0
1/
b101 %
b101 )
b101 '
#60000
b10 -
b10 0
b1 ,
b1 3
0/
12
b110 %
b110 )
b110 '
#70000
b1 -
b1 0
1/
b111 %
b111 )
b111 '
#80000
b10 -
b10 0
b10 ,
b10 3
b10 +
b10 6
b1 *
b1 9
0/
02
05
18
b1000 %
b1000 )
b1000 '
#90000
b1 -
b1 0
1/
b1001 %
b1001 )
b1001 '
#100000
b10 -
b10 0
b1 ,
b1 3
0/
12
b1010 %
b1010 )
b1010 '
#110000
b1 -
b1 0
1/
b1011 %
b1011 )
b1011 '
#120000
b10 -
b10 0
b10 ,
b10 3
b1 +
b1 6
0/
02
15
b1100 %
b1100 )
b1100 '
#130000
b1 -
b1 0
1/
b1101 %
b1101 )
b1101 '
#140000
b10 -
b10 0
b1 ,
b1 3
0/
12
b1110 %
b1110 )
b1110 '
#150000
b1 -
b1 0
1/
b1111 %
b1111 )
b1111 '
#160000
1"
0!
b100 -
b100 0
b10 ,
b10 3
b10 +
b10 6
b10 *
b10 9
0/
02
05
08
1.
b0 %
b0 )
b1 $
b1 (
b1 &
b0 '
#170000
0"
1#
b10 -
b10 0
1/
b1 %
b1 )
b1 '
#180000
1!
0#
b100 -
b100 0
b1 ,
b1 3
0/
12
b10 %
b10 )
b10 '
#190000
b10 -
b10 0
1/
b11 %
b11 )
b11 '
#200000
b100 -
b100 0
b10 ,
b10 3
b1 +
b1 6
0/
02
15
b100 %
b100 )
b100 '
#210000
b10 -
b10 0
1/
b101 %
b101 )
b101 '
#220000
b100 -
b100 0
b1 ,
b1 3
0/
12
b110 %
b110 )
b110 '
#230000
b10 -
b10 0
1/
b111 %
b111 )
b111 '
#240000
b100 -
b100 0
b10 ,
b10 3
b10 +
b10 6
b1 *
b1 9
0/
02
05
18
b1000 %
b1000 )
b1000 '
#250000
b10 -
b10 0
1/
b1001 %
b1001 )
b1001 '
#260000
b100 -
b100 0
b1 ,
b1 3
0/
12
b1010 %
b1010 )
b1010 '
#270000
b10 -
b10 0
1/
b1011 %
b1011 )
b1011 '
#280000
b100 -
b100 0
b10 ,
b10 3
b1 +
b1 6
0/
02
15
b1100 %
b1100 )
b1100 '
#290000
b10 -
b10 0
1/
b1101 %
b1101 )
b1101 '
#300000
b100 -
b100 0
b1 ,
b1 3
0/
12
b1110 %
b1110 )
b1110 '
#310000
b10 -
b10 0
1/
b1111 %
b1111 )
b1111 '
#320000
1"
0!
b100 ,
b100 3
b10 +
b10 6
b10 *
b10 9
0/
02
05
08
0.
11
b0 %
b0 )
b10 $
b10 (
b10 &
b0 '
#330000
b1 -
b1 0
1/
b1 %
b1 )
b1 '
#340000
0"
1#
b10 ,
b10 3
b10 -
b10 0
0/
12
b10 %
b10 )
b10 '
#350000
0#
1!
b1 -
b1 0
1/
b11 %
b11 )
b11 '
#360000
1!
b100 ,
b100 3
b10 -
b10 0
b1 +
b1 6
0/
02
15
b100 %
b100 )
b100 '
#370000
b1 -
b1 0
1/
b101 %
b101 )
b101 '
#380000
b10 ,
b10 3
b10 -
b10 0
0/
12
b110 %
b110 )
b110 '
#390000
b1 -
b1 0
1/
b111 %
b111 )
b111 '
#400000
b100 ,
b100 3
b10 -
b10 0
b10 +
b10 6
b1 *
b1 9
0/
02
05
18
b1000 %
b1000 )
b1000 '
#410000
b1 -
b1 0
1/
b1001 %
b1001 )
b1001 '
#420000
b10 ,
b10 3
b10 -
b10 0
0/
12
b1010 %
b1010 )
b1010 '
#430000
b1 -
b1 0
1/
b1011 %
b1011 )
b1011 '
#440000
b100 ,
b100 3
b10 -
b10 0
b1 +
b1 6
0/
02
15
b1100 %
b1100 )
b1100 '
#450000
b1 -
b1 0
1/
b1101 %
b1101 )
b1101 '
#460000
b10 ,
b10 3
b10 -
b10 0
0/
12
b1110 %
b1110 )
b1110 '
#470000
b1 -
b1 0
1/
b1111 %
b1111 )
b1111 '
#480000
1"
0!
b100 ,
b100 3
b100 -
b100 0
b10 +
b10 6
b10 *
b10 9
0/
02
05
08
1.
b0 %
b0 )
b11 $
b11 (
b11 &
b0 '
#490000
b10 -
b10 0
1/
b1 %
b1 )
b1 '
#500000
b100 -
b100 0
b10 ,
b10 3
0/
12
b10 %
b10 )
b10 '
#510000
0"
1#
b10 -
b10 0
1/
b11 %
b11 )
b11 '
#520000
1!
0#
b100 -
b100 0
b100 ,
b100 3
b1 +
b1 6
0/
02
15
b100 %
b100 )
b100 '
#530000
b10 -
b10 0
1/
b101 %
b101 )
b101 '
#540000
b100 -
b100 0
b10 ,
b10 3
0/
12
b110 %
b110 )
b110 '
#550000
b10 -
b10 0
1/
b111 %
b111 )
b111 '
#560000
b100 -
b100 0
b100 ,
b100 3
b10 +
b10 6
b1 *
b1 9
0/
02
05
18
b1000 %
b1000 )
b1000 '
#570000
b10 -
b10 0
1/
b1001 %
b1001 )
b1001 '
#580000
b100 -
b100 0
b10 ,
b10 3
0/
12
b1010 %
b1010 )
b1010 '
#590000
b10 -
b10 0
1/
b1011 %
b1011 )
b1011 '
#600000
b100 -
b100 0
b100 ,
b100 3
b1 +
b1 6
0/
02
15
b1100 %
b1100 )
b1100 '
#610000
b10 -
b10 0
1/
b1101 %
b1101 )
b1101 '
#620000
b100 -
b100 0
b10 ,
b10 3
0/
12
b1110 %
b1110 )
b1110 '
#630000
b10 -
b10 0
1/
b1111 %
b1111 )
b1111 '
#640000
1"
0!
b100 +
b100 6
b10 *
b10 9
0/
02
05
08
0.
01
14
b0 %
b0 )
b100 $
b100 (
b100 &
b0 '
#650000
b1 -
b1 0
1/
b1 %
b1 )
b1 '
#660000
b10 -
b10 0
b1 ,
b1 3
0/
12
b10 %
b10 )
b10 '
#670000
b1 -
b1 0
1/
b11 %
b11 )
b11 '
#680000
0"
1#
b10 +
b10 6
b10 -
b10 0
b10 ,
b10 3
0/
02
15
b100 %
b100 )
b100 '
#690000
0#
1!
b1 -
b1 0
1/
b101 %
b101 )
b101 '
#700000
b10 -
b10 0
b1 ,
b1 3
0/
12
b110 %
b110 )
b110 '
#710000
b1 -
b1 0
1/
b111 %
b111 )
b111 '
#720000
b100 +
b100 6
b10 -
b10 0
b10 ,
b10 3
b1 *
b1 9
0/
02
05
18
b1000 %
b1000 )
b1000 '
#730000
b1 -
b1 0
1/
b1001 %
b1001 )
b1001 '
#740000
b10 -
b10 0
b1 ,
b1 3
0/
12
b1010 %
b1010 )
b1010 '
#750000
b1 -
b1 0
1/
b1011 %
b1011 )
b1011 '
#760000
b10 +
b10 6
b10 -
b10 0
b10 ,
b10 3
0/
02
15
b1100 %
b1100 )
b1100 '
#770000
b1 -
b1 0
1/
b1101 %
b1101 )
b1101 '
#780000
b10 -
b10 0
b1 ,
b1 3
0/
12
b1110 %
b1110 )
b1110 '
#790000
b1 -
b1 0
1/
b1111 %
b1111 )
b1111 '
#800000
1"
0!
b100 +
b100 6
b100 -
b100 0
b10 ,
b10 3
b10 *
b10 9
0/
02
05
08
1.
b0 %
b0 )
b101 $
b101 (
b101 &
b0 '
#810000
b10 -
b10 0
1/
b1 %
b1 )
b1 '
#820000
b100 -
b100 0
b1 ,
b1 3
0/
12
b10 %
b10 )
b10 '
#830000
b10 -
b10 0
1/
b11 %
b11 )
b11 '
#840000
b100 -
b100 0
b10 +
b10 6
b10 ,
b10 3
0/
02
15
b100 %
b100 )
b100 '
#850000
0"
1#
b10 -
b10 0
1/
b101 %
b101 )
b101 '
#860000
1!
0#
b100 -
b100 0
b1 ,
b1 3
0/
12
b110 %
b110 )
b110 '
#870000
b10 -
b10 0
1/
b111 %
b111 )
b111 '
#880000
b100 -
b100 0
b100 +
b100 6
b10 ,
b10 3
b1 *
b1 9
0/
02
05
18
b1000 %
b1000 )
b1000 '
#890000
b10 -
b10 0
1/
b1001 %
b1001 )
b1001 '
#900000
b100 -
b100 0
b1 ,
b1 3
0/
12
b1010 %
b1010 )
b1010 '
#910000
b10 -
b10 0
1/
b1011 %
b1011 )
b1011 '
#920000
b100 -
b100 0
b10 +
b10 6
b10 ,
b10 3
0/
02
15
b1100 %
b1100 )
b1100 '
#930000
b10 -
b10 0
1/
b1101 %
b1101 )
b1101 '
#940000
b100 -
b100 0
b1 ,
b1 3
0/
12
b1110 %
b1110 )
b1110 '
#950000
b10 -
b10 0
1/
b1111 %
b1111 )
b1111 '
#960000
1"
0!
b100 +
b100 6
b100 ,
b100 3
b10 *
b10 9
0/
02
05
08
0.
11
b0 %
b0 )
b110 $
b110 (
b110 &
b0 '
#970000
b1 -
b1 0
1/
b1 %
b1 )
b1 '
#980000
b10 ,
b10 3
b10 -
b10 0
0/
12
b10 %
b10 )
b10 '
#990000
b1 -
b1 0
1/
b11 %
b11 )
b11 '
#1000000
b100 ,
b100 3
b10 +
b10 6
b10 -
b10 0
0/
02
15
b100 %
b100 )
b100 '
#1010000
b1 -
b1 0
1/
b101 %
b101 )
b101 '
#1020000
0"
1#
b10 ,
b10 3
b10 -
b10 0
0/
12
b110 %
b110 )
b110 '
#1030000
0#
1!
b1 -
b1 0
1/
b111 %
b111 )
b111 '
#1040000
b100 ,
b100 3
b100 +
b100 6
b10 -
b10 0
b1 *
b1 9
0/
02
05
18
b1000 %
b1000 )
b1000 '
#1050000
b1 -
b1 0
1/
b1001 %
b1001 )
b1001 '
#1060000
b10 ,
b10 3
b10 -
b10 0
0/
12
b1010 %
b1010 )
b1010 '
#1070000
b1 -
b1 0
1/
b1011 %
b1011 )
b1011 '
#1080000
b100 ,
b100 3
b10 +
b10 6
b10 -
b10 0
0/
02
15
b1100 %
b1100 )
b1100 '
#1090000
b1 -
b1 0
1/
b1101 %
b1101 )
b1101 '
#1100000
b10 ,
b10 3
b10 -
b10 0
0/
12
b1110 %
b1110 )
b1110 '
#1110000
b1 -
b1 0
1/
b1111 %
b1111 )
b1111 '
#1120000
1"
0!
b100 ,
b100 3
b100 +
b100 6
b100 -
b100 0
b10 *
b10 9
0/
02
05
08
1.
b0 %
b0 )
b111 $
b111 (
b111 &
b0 '
#1130000
b10 -
b10 0
1/
b1 %
b1 )
b1 '
#1140000
b100 -
b100 0
b10 ,
b10 3
0/
12
b10 %
b10 )
b10 '
#1150000
b10 -
b10 0
1/
b11 %
b11 )
b11 '
#1160000
b100 -
b100 0
b100 ,
b100 3
b10 +
b10 6
0/
02
15
b100 %
b100 )
b100 '
#1170000
b10 -
b10 0
1/
b101 %
b101 )
b101 '
#1180000
b100 -
b100 0
b10 ,
b10 3
0/
12
b110 %
b110 )
b110 '
#1190000
0"
1#
b10 -
b10 0
1/
b111 %
b111 )
b111 '
#1200000
1!
0#
b100 -
b100 0
b100 ,
b100 3
b100 +
b100 6
b1 *
b1 9
0/
02
05
18
b1000 %
b1000 )
b1000 '
#1210000
b10 -
b10 0
1/
b1001 %
b1001 )
b1001 '
#1220000
b100 -
b100 0
b10 ,
b10 3
0/
12
b1010 %
b1010 )
b1010 '
#1230000
b10 -
b10 0
1/
b1011 %
b1011 )
b1011 '
#1240000
b100 -
b100 0
b100 ,
b100 3
b10 +
b10 6
0/
02
15
b1100 %
b1100 )
b1100 '
#1250000
b10 -
b10 0
1/
b1101 %
b1101 )
b1101 '
#1260000
b100 -
b100 0
b10 ,
b10 3
0/
12
b1110 %
b1110 )
b1110 '
#1270000
b10 -
b10 0
1/
b1111 %
b1111 )
b1111 '
#1280000
1"
0!
b100 *
b100 9
0/
02
05
08
0.
01
04
17
b0 %
b0 )
b1000 $
b1000 (
b1000 &
b0 '
#1290000
b1 -
b1 0
1/
b1 %
b1 )
b1 '
#1300000
b10 -
b10 0
b1 ,
b1 3
0/
12
b10 %
b10 )
b10 '
#1310000
b1 -
b1 0
1/
b11 %
b11 )
b11 '
#1320000
b10 -
b10 0
b10 ,
b10 3
b1 +
b1 6
0/
02
15
b100 %
b100 )
b100 '
#1330000
b1 -
b1 0
1/
b101 %
b101 )
b101 '
#1340000
b10 -
b10 0
b1 ,
b1 3
0/
12
b110 %
b110 )
b110 '
#1350000
b1 -
b1 0
1/
b111 %
b111 )
b111 '
#1360000
0"
1#
b10 *
b10 9
b10 -
b10 0
b10 ,
b10 3
b10 +
b10 6
0/
02
05
18
b1000 %
b1000 )
b1000 '
#1370000
0#
1!
b1 -
b1 0
1/
b1001 %
b1001 )
b1001 '
#1380000
b10 -
b10 0
b1 ,
b1 3
0/
12
b1010 %
b1010 )
b1010 '
#1390000
b1 -
b1 0
1/
b1011 %
b1011 )
b1011 '
#1400000
b10 -
b10 0
b10 ,
b10 3
b1 +
b1 6
0/
02
15
b1100 %
b1100 )
b1100 '
#1410000
b1 -
b1 0
1/
b1101 %
b1101 )
b1101 '
#1420000
b10 -
b10 0
b1 ,
b1 3
0/
12
b1110 %
b1110 )
b1110 '
#1430000
b1 -
b1 0
1/
b1111 %
b1111 )
b1111 '
#1440000
0!
1"
b100 *
b100 9
b100 -
b100 0
b10 ,
b10 3
b10 +
b10 6
0/
02
05
08
1.
b0 %
b0 )
b1001 $
b1001 (
b1001 &
b0 '
#1450000
b10 -
b10 0
1/
b1 %
b1 )
b1 '
#1460000
b100 -
b100 0
b1 ,
b1 3
0/
12
b10 %
b10 )
b10 '
#1470000
b10 -
b10 0
1/
b11 %
b11 )
b11 '
#1480000
b100 -
b100 0
b10 ,
b10 3
b1 +
b1 6
0/
02
15
b100 %
b100 )
b100 '
#1490000
b10 -
b10 0
1/
b101 %
b101 )
b101 '
#1500000
b100 -
b100 0
b1 ,
b1 3
0/
12
b110 %
b110 )
b110 '
#1510000
b10 -
b10 0
1/
b111 %
b111 )
b111 '
#1520000
b100 -
b100 0
b10 *
b10 9
b10 ,
b10 3
b10 +
b10 6
0/
02
05
18
b1000 %
b1000 )
b1000 '
#1530000
0"
1#
b10 -
b10 0
1/
b1001 %
b1001 )
b1001 '
#1540000
1!
0#
b100 -
b100 0
b1 ,
b1 3
0/
12
b1010 %
b1010 )
b1010 '
#1550000
b10 -
b10 0
1/
b1011 %
b1011 )
b1011 '
#1560000
b100 -
b100 0
b10 ,
b10 3
b1 +
b1 6
0/
02
15
b1100 %
b1100 )
b1100 '
#1570000
b10 -
b10 0
1/
b1101 %
b1101 )
b1101 '
#1580000
b100 -
b100 0
b1 ,
b1 3
0/
12
b1110 %
b1110 )
b1110 '
#1590000
b10 -
b10 0
1/
b1111 %
b1111 )
b1111 '
#1600000
0!
1"
b100 *
b100 9
b100 ,
b100 3
b10 +
b10 6
0/
02
05
08
0.
11
b0 %
b0 )
b1010 $
b1010 (
b1010 &
b0 '
#1610000
b1 -
b1 0
1/
b1 %
b1 )
b1 '
#1620000
b10 ,
b10 3
b10 -
b10 0
0/
12
b10 %
b10 )
b10 '
#1630000
b1 -
b1 0
1/
b11 %
b11 )
b11 '
#1640000
b100 ,
b100 3
b10 -
b10 0
b1 +
b1 6
0/
02
15
b100 %
b100 )
b100 '
#1650000
b1 -
b1 0
1/
b101 %
b101 )
b101 '
#1660000
b10 ,
b10 3
b10 -
b10 0
0/
12
b110 %
b110 )
b110 '
#1670000
b1 -
b1 0
1/
b111 %
b111 )
b111 '
#1680000
b100 ,
b100 3
b10 *
b10 9
b10 -
b10 0
b10 +
b10 6
0/
02
05
18
b1000 %
b1000 )
b1000 '
#1690000
b1 -
b1 0
1/
b1001 %
b1001 )
b1001 '
#1700000
0"
1#
b10 ,
b10 3
b10 -
b10 0
0/
12
b1010 %
b1010 )
b1010 '
#1710000
0#
1!
b1 -
b1 0
1/
b1011 %
b1011 )
b1011 '
#1720000
1!
b100 ,
b100 3
b10 -
b10 0
b1 +
b1 6
0/
02
15
b1100 %
b1100 )
b1100 '
#1730000
b1 -
b1 0
1/
b1101 %
b1101 )
b1101 '
#1740000
b10 ,
b10 3
b10 -
b10 0
0/
12
b1110 %
b1110 )
b1110 '
#1750000
b1 -
b1 0
1/
b1111 %
b1111 )
b1111 '
#1760000
0!
1"
b100 ,
b100 3
b100 *
b100 9
b100 -
b100 0
b10 +
b10 6
0/
02
05
08
1.
b0 %
b0 )
b1011 $
b1011 (
b1011 &
b0 '
#1770000
b10 -
b10 0
1/
b1 %
b1 )
b1 '
#1780000
b100 -
b100 0
b10 ,
b10 3
0/
12
b10 %
b10 )
b10 '
#1790000
b10 -
b10 0
1/
b11 %
b11 )
b11 '
#1800000
b100 -
b100 0
b100 ,
b100 3
b1 +
b1 6
0/
02
15
b100 %
b100 )
b100 '
#1810000
b10 -
b10 0
1/
b101 %
b101 )
b101 '
#1820000
b100 -
b100 0
b10 ,
b10 3
0/
12
b110 %
b110 )
b110 '
#1830000
b10 -
b10 0
1/
b111 %
b111 )
b111 '
#1840000
b100 -
b100 0
b100 ,
b100 3
b10 *
b10 9
b10 +
b10 6
0/
02
05
18
b1000 %
b1000 )
b1000 '
#1850000
b10 -
b10 0
1/
b1001 %
b1001 )
b1001 '
#1860000
b100 -
b100 0
b10 ,
b10 3
0/
12
b1010 %
b1010 )
b1010 '
#1870000
0"
1#
b10 -
b10 0
1/
b1011 %
b1011 )
b1011 '
#1880000
1!
0#
b100 -
b100 0
b100 ,
b100 3
b1 +
b1 6
0/
02
15
b1100 %
b1100 )
b1100 '
#1890000
b10 -
b10 0
1/
b1101 %
b1101 )
b1101 '
#1900000
b100 -
b100 0
b10 ,
b10 3
0/
12
b1110 %
b1110 )
b1110 '
#1910000
b10 -
b10 0
1/
b1111 %
b1111 )
b1111 '
#1920000
0!
1"
b100 *
b100 9
b100 +
b100 6
0/
02
05
08
0.
01
14
b0 %
b0 )
b1100 $
b1100 (
b1100 &
b0 '
#1930000
b1 -
b1 0
1/
b1 %
b1 )
b1 '
#1940000
b10 -
b10 0
b1 ,
b1 3
0/
12
b10 %
b10 )
b10 '
#1950000
b1 -
b1 0
1/
b11 %
b11 )
b11 '
#1960000
b10 +
b10 6
b10 -
b10 0
b10 ,
b10 3
0/
02
15
b100 %
b100 )
b100 '
#1970000
b1 -
b1 0
1/
b101 %
b101 )
b101 '
#1980000
b10 -
b10 0
b1 ,
b1 3
0/
12
b110 %
b110 )
b110 '
#1990000
b1 -
b1 0
1/
b111 %
b111 )
b111 '
#2000000
b100 +
b100 6
b10 *
b10 9
b10 -
b10 0
b10 ,
b10 3
0/
02
05
18
b1000 %
b1000 )
b1000 '
#2010000
b1 -
b1 0
1/
b1001 %
b1001 )
b1001 '
#2020000
b10 -
b10 0
b1 ,
b1 3
0/
12
b1010 %
b1010 )
b1010 '
#2030000
b1 -
b1 0
1/
b1011 %
b1011 )
b1011 '
#2040000
0"
1#
b10 +
b10 6
b10 -
b10 0
b10 ,
b10 3
0/
02
15
b1100 %
b1100 )
b1100 '
#2050000
0#
1!
b1 -
b1 0
1/
b1101 %
b1101 )
b1101 '
#2060000
b10 -
b10 0
b1 ,
b1 3
0/
12
b1110 %
b1110 )
b1110 '
#2070000
b1 -
b1 0
1/
b1111 %
b1111 )
b1111 '
#2080000
1"
0!
b100 +
b100 6
b100 *
b100 9
b100 -
b100 0
b10 ,
b10 3
0/
02
05
08
1.
b0 %
b0 )
b1101 $
b1101 (
b1101 &
b0 '
#2090000
b10 -
b10 0
1/
b1 %
b1 )
b1 '
#2100000
b100 -
b100 0
b1 ,
b1 3
0/
12
b10 %
b10 )
b10 '
#2110000
b10 -
b10 0
1/
b11 %
b11 )
b11 '
#2120000
b100 -
b100 0
b10 +
b10 6
b10 ,
b10 3
0/
02
15
b100 %
b100 )
b100 '
#2130000
b10 -
b10 0
1/
b101 %
b101 )
b101 '
#2140000
b100 -
b100 0
b1 ,
b1 3
0/
12
b110 %
b110 )
b110 '
#2150000
b10 -
b10 0
1/
b111 %
b111 )
b111 '
#2160000
b100 -
b100 0
b100 +
b100 6
b10 *
b10 9
b10 ,
b10 3
0/
02
05
18
b1000 %
b1000 )
b1000 '
#2170000
b10 -
b10 0
1/
b1001 %
b1001 )
b1001 '
#2180000
b100 -
b100 0
b1 ,
b1 3
0/
12
b1010 %
b1010 )
b1010 '
#2190000
b10 -
b10 0
1/
b1011 %
b1011 )
b1011 '
#2200000
b100 -
b100 0
b10 +
b10 6
b10 ,
b10 3
0/
02
15
b1100 %
b1100 )
b1100 '
#2210000
0"
1#
b10 -
b10 0
1/
b1101 %
b1101 )
b1101 '
#2220000
1!
0#
b100 -
b100 0
b1 ,
b1 3
0/
12
b1110 %
b1110 )
b1110 '
#2230000
b10 -
b10 0
1/
b1111 %
b1111 )
b1111 '
#2240000
1"
0!
b100 +
b100 6
b100 *
b100 9
b100 ,
b100 3
0/
02
05
08
0.
11
b0 %
b0 )
b1110 $
b1110 (
b1110 &
b0 '
#2250000
b1 -
b1 0
1/
b1 %
b1 )
b1 '
#2260000
b10 ,
b10 3
b10 -
b10 0
0/
12
b10 %
b10 )
b10 '
#2270000
b1 -
b1 0
1/
b11 %
b11 )
b11 '
#2280000
b100 ,
b100 3
b10 +
b10 6
b10 -
b10 0
0/
02
15
b100 %
b100 )
b100 '
#2290000
b1 -
b1 0
1/
b101 %
b101 )
b101 '
#2300000
b10 ,
b10 3
b10 -
b10 0
0/
12
b110 %
b110 )
b110 '
#2310000
b1 -
b1 0
1/
b111 %
b111 )
b111 '
#2320000
b100 ,
b100 3
b100 +
b100 6
b10 *
b10 9
b10 -
b10 0
0/
02
05
18
b1000 %
b1000 )
b1000 '
#2330000
b1 -
b1 0
1/
b1001 %
b1001 )
b1001 '
#2340000
b10 ,
b10 3
b10 -
b10 0
0/
12
b1010 %
b1010 )
b1010 '
#2350000
b1 -
b1 0
1/
b1011 %
b1011 )
b1011 '
#2360000
b100 ,
b100 3
b10 +
b10 6
b10 -
b10 0
0/
02
15
b1100 %
b1100 )
b1100 '
#2370000
b1 -
b1 0
1/
b1101 %
b1101 )
b1101 '
#2380000
0"
1#
b10 ,
b10 3
b10 -
b10 0
0/
12
b1110 %
b1110 )
b1110 '
#2390000
0#
1!
b1 -
b1 0
1/
b1111 %
b1111 )
b1111 '
#2400000
1"
0!
b100 ,
b100 3
b100 +
b100 6
b100 *
b100 9
b100 -
b100 0
0/
02
05
08
1.
b0 %
b0 )
b1111 $
b1111 (
b1111 &
b0 '
#2410000
b10 -
b10 0
1/
b1 %
b1 )
b1 '
#2420000
b100 -
b100 0
b10 ,
b10 3
0/
12
b10 %
b10 )
b10 '
#2430000
b10 -
b10 0
1/
b11 %
b11 )
b11 '
#2440000
b100 -
b100 0
b100 ,
b100 3
b10 +
b10 6
0/
02
15
b100 %
b100 )
b100 '
#2450000
b10 -
b10 0
1/
b101 %
b101 )
b101 '
#2460000
b100 -
b100 0
b10 ,
b10 3
0/
12
b110 %
b110 )
b110 '
#2470000
b10 -
b10 0
1/
b111 %
b111 )
b111 '
#2480000
b100 -
b100 0
b100 ,
b100 3
b100 +
b100 6
b10 *
b10 9
0/
02
05
18
b1000 %
b1000 )
b1000 '
#2490000
b10 -
b10 0
1/
b1001 %
b1001 )
b1001 '
#2500000
b100 -
b100 0
b10 ,
b10 3
0/
12
b1010 %
b1010 )
b1010 '
#2510000
b10 -
b10 0
1/
b1011 %
b1011 )
b1011 '
#2520000
b100 -
b100 0
b100 ,
b100 3
b10 +
b10 6
0/
02
15
b1100 %
b1100 )
b1100 '
#2530000
b10 -
b10 0
1/
b1101 %
b1101 )
b1101 '
#2540000
b100 -
b100 0
b10 ,
b10 3
0/
12
b1110 %
b1110 )
b1110 '
#2550000
0"
1#
b10 -
b10 0
1/
b1111 %
b1111 )
b1111 '
#2560000
b10000 &
b10000 '
