Tff/Tff.v
module tff (T, clk, q, qbar, rst);
    input wire T, clk, rst;
    output reg q, qbar;
    always @(posedge clk or posedge rst) begin
        if (rst) begin
            q <= 1'b0;
            qbar <= 1'b0;
        end
        else if (T) begin
            q <= ~q;
            qbar <= ~qbar;
        end
    end

endmodule

Tff/Tff_tb.v
`timescale 1ns/1ps

module Tff_tb;

  // Inputs
  reg clk;
  reg rst;
  reg t;

  // Outputs
  wire q;
  wire qbar;

  // Instantiate the Unit Under Test (UUT)
  tff uut (
    .clk(clk), 
    .rst(rst), 
    .T(t), 
    .q(q), 
    .qbar(qbar)
  );
always #5 clk = ~clk; // Clock generation
  initial begin
    $dumpfile("Tff.vcd");
    $dumpvars(0, Tff_tb);
    // Initialize Inputs
    clk = 0;
    rst = 0;
    t = 0;

    // Wait for global reset to finish
    #10;
        
    // Add stimulus here
    rst = 1; #10; rst = 0; // Reset the flip-flop

    t = 1; #20; // Toggle input high
    t = 0; #20; // Toggle input low
    t = 1; #20; // Toggle input high again
    t = 0; #20; // Toggle input low again

    $finish; // End simulation
  end

endmodule

Tff/Tff.vcd
$date
	Mon Sep 28 05:57:33 2026
$end
$version
	Icarus Verilog
$end
$timescale
	1ps
$end
$scope module Tff_tb $end
$var wire 1 ! qbar $end
$var wire 1 " q $end
$var reg 1 # clk $end
$var reg 1 $ rst $end
$var reg 1 % t $end
$scope module uut $end
$var wire 1 % T $end
$var wire 1 # clk $end
$var wire 1 $ rst $end
$var reg 1 " q $end
$var reg 1 ! qbar $end
$upscope $end
$upscope $end
$enddefinitions $end
#0
$dumpvars
0%
0$
0#
x"
x!
$end
#5000
1#
#10000
0!
0"
0#
1$
#15000
1#
#20000
0#
1%
0$
#25000
1!
1"
1#
#30000
0#
#35000
0!
0"
1#
#40000
0#
0%
#45000
1#
#50000
0#
#55000
1#
#60000
0#
1%
#65000
1!
1"
1#
#70000
0#
#75000
0!
0"
1#
#80000
0#
0%
