mux4_1/mux4_1.v
module mux4_1(
input I0,
input I1,
input I2,
input I3,
input wire [1:0] sel,
output reg y);

always @(*) begin
   case (sel)
        2'b00: y = I0;
        2'b01: y = I1;
        2'b10: y = I2;
        2'b11: y = I3;
  endcase
end
endmodule

mux4_1/mux4_1_tb.v
`timescale 1ns/1ps

module mux4_1_tb;

    reg I0;
    reg I1;
    reg I2;
    reg I3;
    reg [1:0] sel;

    wire y;

    // Instantiate DUT
    mux4_1 uut (
        .I0(I0),
        .I1(I1),
        .I2(I2),
        .I3(I3),
        .sel(sel),
        .y(y)
    );

    // Generate VCD for GTKWave
    initial begin
        $dumpfile("mux4_1.vcd");
        $dumpvars(0, mux4_1_tb);
    end

    // Display values
    initial begin
        $display("Time\tI0 I1 I2 I3\tsel\ty");
        $monitor("%0t\t%b  %b  %b  %b\t%b\t%b",
                 $time, I0, I1, I2, I3, sel, y);
    end

    // Test all combinations
    initial begin

        // sel = 00 -> y should follow I0
        I0=0; I1=0; I2=0; I3=0; sel=2'b00; #10;
        I0=1; I1=0; I2=0; I3=0; sel=2'b00; #10;
        I0=0; I1=1; I2=0; I3=0; sel=2'b00; #10;
        I0=1; I1=1; I2=0; I3=0; sel=2'b00; #10;

        // sel = 01 -> y should follow I1
        I0=0; I1=0; I2=0; I3=0; sel=2'b01; #10;
        I0=0; I1=1; I2=0; I3=0; sel=2'b01; #10;
        I0=0; I1=0; I2=1; I3=0; sel=2'b01; #10;
        I0=0; I1=1; I2=1; I3=0; sel=2'b01; #10;

        // sel = 10 -> y should follow I2
        I0=0; I1=0; I2=0; I3=0; sel=2'b10; #10;
        I0=0; I1=0; I2=1; I3=0; sel=2'b10; #10;
        I0=1; I1=0; I2=0; I3=0; sel=2'b10; #10;
        I0=1; I1=0; I2=1; I3=0; sel=2'b10; #10;

        // sel = 11 -> y should follow I3
        I0=0; I1=0; I2=0; I3=0; sel=2'b11; #10;
        I0=0; I1=0; I2=0; I3=1; sel=2'b11; #10;
        I0=1; I1=0; I2=0; I3=0; sel=2'b11; #10;
        I0=1; I1=1; I2=1; I3=1; sel=2'b11; #10;

        $finish;
    end

endmodule

mux4_1/mux4_1.vcd
$date
	Sun Aug  9 06:07:13 2026
$end
$version
	Icarus Verilog
$end
$timescale
	1ps
$end
$scope module mux4_1_tb $end
$var wire 1 ! y $end
$var reg 1 " I0 $end
$var reg 1 # I1 $end
$var reg 1 $ I2 $end
$var reg 1 % I3 $end
$var reg 2 & sel [1:0] $end
$scope module uut $end
$var wire 1 " I0 $end
$var wire 1 # I1 $end
$var wire 1 $ I2 $end
$var wire 1 % I3 $end
$var wire 2 ' sel [1:0] $end
$var reg 1 ! y $end
$upscope $end
$upscope $end
$enddefinitions $end
#0
$dumpvars
b0 '
b0 &
0%
0$
0#
0"
0!
$end
#10000
1!
1"
#20000
0!
1#
0"
#30000
1!
1"
#40000
0!
b1 &
b1 '
0#
0"
#50000
1!
1#
#60000
0!
1$
0#
#70000
1!
1#
#80000
0!
b10 &
b10 '
0$
0#
#90000
1!
1$
#100000
0!
0$
1"
#110000
1!
1$
#120000
0!
b11 &
b11 '
0$
0"
#130000
1!
1%
#140000
0!
0%
1"
#150000
1!
1%
1$
1#
