Dff/Dff.v
module dff(d, clk, q, qbar);
    input wire d, clk;
    output reg q, qbar;

    always@(posedge clk) begin
        q <= d;
        qbar <= ~d;
    end
endmodule

Dff/Dff_tb.v
`timescale 1ns/1ps

module Dff_tb;
    reg d, clk;
    wire q, qbar;

    dff uut(.d(d), .clk(clk), .q(q), .qbar(qbar));

    always #5 clk = ~clk;

    initial begin
        $dumpfile("Dff.vcd");
        $dumpvars(0, Dff_tb);
    end

    initial begin
        // Test sequence
        clk = 0;
        d = 0; #10;
        d = 1; #10;
        d = 0; #10;
        d = 1; #10;
        d = 0; #10;
        $finish;
    end

    initial begin
        $monitor("Time: %0t | d: %b | clk: %b | q: %b | qbar: %b", $time, d, clk, q, qbar);
    end
endmodule

Dff/Dff.vcd
$date
	Wed Sep 23 14:34:40 2026
$end
$version
	Icarus Verilog
$end
$timescale
	1ps
$end
$scope module Dff_tb $end
$var wire 1 ! qbar $end
$var wire 1 " q $end
$var reg 1 # clk $end
$var reg 1 $ d $end
$scope module uut $end
$var wire 1 # clk $end
$var wire 1 $ d $end
$var reg 1 " q $end
$var reg 1 ! qbar $end
$upscope $end
$upscope $end
$enddefinitions $end
#0
$dumpvars
0$
0#
x"
x!
$end
#5000
1!
0"
1#
#10000
0#
1$
#15000
0!
1"
1#
#20000
0#
0$
#25000
1!
0"
1#
#30000
0#
1$
#35000
0!
1"
1#
#40000
0#
0$
#45000
1!
0"
1#
