mux2_1/mux2_1.v
module mux2_1(
input a,
input b,
input s0,
output y);

assign y = s0 ? b : a;
endmodule

mux2_1/mux2_1_tb.v
`timescale 1ns/1ps

module mux2_1_tb;

    reg a, b, s0;
    wire y;

    // Instantiate the DUT
    mux2_1 uut (
        .a(a),
        .b(b),
        .s0(s0),
        .y(y)
    );

    // Generate VCD file
    initial begin
        $dumpfile("mux2_1.vcd");
        $dumpvars(0, mux2_1_tb);
    end

    // Display outputs
    initial begin
        $display("Time\ta\tb\tsel\ty");
        $monitor("%0t\t%b\t%b\t%b\t%b", $time, a, b, s0, y);
    end

    // Test vectors
    initial begin
        a=0; b=0; s0=0; #10;
        a=0; b=1; s0=0; #10;
        a=1; b=0; s0=0; #10;
        a=1; b=1; s0=0; #10;

        a=0; b=0; s0=1; #10;
        a=0; b=1; s0=1; #10;
        a=1; b=0; s0=1; #10;
        a=1; b=1; s0=1; #10;

        $finish;
    end

endmodule

mux2_1/mux2_1.vcd
$date
	Fri Aug  7 09:31:26 2026
$end
$version
	Icarus Verilog
$end
$timescale
	1ps
$end
$scope module mux2_1_tb $end
$var wire 1 ! y $end
$var reg 1 " a $end
$var reg 1 # b $end
$var reg 1 $ s0 $end
$scope module uut $end
$var wire 1 " a $end
$var wire 1 # b $end
$var wire 1 $ s0 $end
$var wire 1 ! y $end
$upscope $end
$upscope $end
$enddefinitions $end
#0
$dumpvars
0$
0#
0"
0!
$end
#10000
1#
#20000
1!
0#
1"
#30000
1#
#40000
0!
1$
0#
0"
#50000
1!
1#
#60000
0!
0#
1"
#70000
1!
1#
