priority_encoder/p_encoder.v
module p_encoder (i, y);
    input wire  [3:0] i;
    output reg [1:0] y;

    always@ (i) begin
        casez (i)
            4'b0001 : y = 2'b00;
            4'b001? : y = 2'b01;
            4'b01?? : y = 2'b10;
            4'b1??? : y = 2'b11;
        endcase
    end
endmodule

priority_encoder/p_encoder_tb.v
`timescale 1ns/1ps

module p_encoder_tb;

    reg  [3:0] i;
    wire [1:0] y;

    integer k;

    p_encoder uut (
        .i(i),
        .y(y)
    );

    initial begin

        $dumpfile("p_encoder.vcd");
        $dumpvars(0, p_encoder_tb);

        $display("--------------------------------");
        $display("   i    |   y");
        $display("--------------------------------");

        for (k = 0; k < 16; k = k + 1) begin

            i = k;
            #10;

            $display("  %04b   |  %02b", i, y);

        end

        $display("--------------------------------");

        $finish;
    end

endmodule

priority_encoder/p_encoder.vcd
$date
	Sun Sep 27 11:13:59 2026
$end
$version
	Icarus Verilog
$end
$timescale
	1ps
$end
$scope module p_encoder_tb $end
$var wire 2 ! y [1:0] $end
$var reg 4 " i [3:0] $end
$var integer 32 # k [31:0] $end
$scope module uut $end
$var wire 4 $ i [3:0] $end
$var reg 2 % y [1:0] $end
$upscope $end
$upscope $end
$enddefinitions $end
#0
$dumpvars
bx %
b0 $
b0 #
b0 "
bx !
$end
#10000
b0 !
b0 %
b1 "
b1 $
b1 #
#20000
b1 !
b1 %
b10 "
b10 $
b10 #
#30000
b11 "
b11 $
b11 #
#40000
b10 !
b10 %
b100 "
b100 $
b100 #
#50000
b101 "
b101 $
b101 #
#60000
b110 "
b110 $
b110 #
#70000
b111 "
b111 $
b111 #
#80000
b11 !
b11 %
b1000 "
b1000 $
b1000 #
#90000
b1001 "
b1001 $
b1001 #
#100000
b1010 "
b1010 $
b1010 #
#110000
b1011 "
b1011 $
b1011 #
#120000
b1100 "
b1100 $
b1100 #
#130000
b1101 "
b1101 $
b1101 #
#140000
b1110 "
b1110 $
b1110 #
#150000
b1111 "
b1111 $
b1111 #
#160000
b10000 #
