mux8_1/mux8_1.v
module mux8_1(
input [0:7] I,
input [2:0] sel,
output reg y);

always @(*) begin
case(sel)
3'b000:y=I[0];
3'b001:y=I[1];
3'b010:y=I[2];
3'b011:y=I[3];
3'b100:y=I[4];
3'b101:y=I[5];
3'b110:y=I[6];
3'b111:y=I[7];
endcase
end
endmodule

mux8_1/mux8_1_tb.v
`timescale 1ns/1ps

module mux8_1_tb;

    reg [7:0] I;
    reg [2:0] sel;
    wire y;

    // Instantiate DUT
    mux8_1 uut (
        .I(I),
        .sel(sel),
        .y(y)
    );

    // Generate VCD file
    initial begin
        $dumpfile("mux8_1.vcd");
        $dumpvars(0, mux8_1_tb);
    end

    // Display results
    initial begin
        $display("Time\tI\t\tSel\tY");
        $monitor("%0t\t%b\t%b\t%b", $time, I, sel, y);
    end

    // Test all 8 select cases
    initial begin

        I = 8'b10101010;

        sel = 3'b000; #10;
        sel = 3'b001; #10;
        sel = 3'b010; #10;
        sel = 3'b011; #10;
        sel = 3'b100; #10;
        sel = 3'b101; #10;
        sel = 3'b110; #10;
        sel = 3'b111; #10;

        $finish;
    end

endmodule

mux8_1/mux8_1.vcd
$date
	Mon Aug 10 12:16:39 2026
$end
$version
	Icarus Verilog
$end
$timescale
	1ps
$end
$scope module mux8_1_tb $end
$var wire 1 ! y $end
$var reg 8 " I [7:0] $end
$var reg 3 # sel [2:0] $end
$scope module uut $end
$var wire 8 $ I [0:7] $end
$var wire 3 % sel [2:0] $end
$var reg 1 ! y $end
$upscope $end
$upscope $end
$enddefinitions $end
#0
$dumpvars
b0 %
b10101010 $
b0 #
b10101010 "
1!
$end
#10000
0!
b1 #
b1 %
#20000
1!
b10 #
b10 %
#30000
0!
b11 #
b11 %
#40000
1!
b100 #
b100 %
#50000
0!
b101 #
b101 %
#60000
1!
b110 #
b110 %
#70000
0!
b111 #
b111 %
