JKff/JKff.v
module jkff (j, k, clk, q, qbar);
    input wire j, k, clk;
    output reg q, qbar;
    always@ (posedge clk) begin
          case ({j, k})
            2'b00: begin
                q <= q;
                qbar <= qbar;
            end
            2'b01: begin
                q <= 1'b0;
                qbar <= 1'b1;
            end
            2'b10: begin
                q <= 1'b1;
                qbar <= 1'b0;
            end
            2'b11: begin
                q <= ~q;
                qbar <= ~qbar;
            end
          endcase
    end
endmodule

JKff/JKff_tb.v
`timescale 1ns/1ps

module jkff_tb;

    reg j, k, clk;
    wire q, qbar;

    integer i;

    jkff uut (
        .j(j),
        .k(k),
        .clk(clk),
        .q(q),
        .qbar(qbar)
    );

    // Clock
    always #5 clk = ~clk;

    initial begin
        $dumpfile("jkff_tb.vcd");
        $dumpvars(0, jkff_tb);

        clk = 0;
        j = 0;
        k = 0;

        $display("Time | CLK | J K | Q Qbar");
        $display("---------------------------");

        $monitor("%4t |  %b  | %b %b | %b   %b",
                 $time, clk, j, k, q, qbar);

        // 16 random J/K combinations
        for (i = 0; i < 16; i = i + 1) begin

            j = $random & 1'b1;
            k = $random & 1'b1;

            #10;

        end

        $finish;
    end

endmodule

JKff/jkff_tb.vcd
$date
	Mon Sep 28 06:05:55 2026
$end
$version
	Icarus Verilog
$end
$timescale
	1ps
$end
$scope module jkff_tb $end
$var wire 1 ! qbar $end
$var wire 1 " q $end
$var reg 1 # clk $end
$var reg 1 $ j $end
$var reg 1 % k $end
$var integer 32 & i [31:0] $end
$scope module uut $end
$var wire 1 # clk $end
$var wire 1 $ j $end
$var wire 1 % k $end
$var reg 1 " q $end
$var reg 1 ! qbar $end
$upscope $end
$upscope $end
$enddefinitions $end
#0
$dumpvars
b0 &
1%
0$
0#
x"
x!
$end
#5000
1!
0"
1#
#10000
0#
1$
b1 &
#15000
0!
1"
1#
#20000
0#
b10 &
#25000
1!
0"
1#
#30000
0#
0%
b11 &
#35000
0!
1"
1#
#40000
0#
1%
b100 &
#45000
1!
0"
1#
#50000
0#
0$
b101 &
#55000
1#
#60000
0#
0%
1$
b110 &
#65000
0!
1"
1#
#70000
0#
b111 &
#75000
1#
#80000
0#
b1000 &
#85000
1#
#90000
0#
1%
b1001 &
#95000
1!
0"
1#
#100000
0#
0$
b1010 &
#105000
1#
#110000
0#
0%
b1011 &
#115000
1#
#120000
0#
1%
b1100 &
#125000
1#
#130000
0#
b1101 &
#135000
1#
#140000
0#
1$
b1110 &
#145000
0!
1"
1#
#150000
0#
0%
b1111 &
#155000
1#
#160000
0#
b10000 &
