Dff/Dff.v
module dff(d, clk, q, qbar);
    input wire d, clk;
    output reg q, qbar;

    always@(posedge clk) begin
        q <= d;
        qbar <= ~d;
    end
endmodule

siso_register/shift_reg.v
module shift_reg(in, clk, out);
    input in;
    input clk;
    output wire out;
    wire m1, m2, m3;
dff dff0(.d(in), .clk(clk), .q(m1), .qbar());
dff dff1(.d(m1), .clk(clk), .q(m2), .qbar());
dff dff2(.d(m2), .clk(clk), .q(m3), .qbar());
dff dff3(.d(m3), .clk(clk), .q(out), .qbar());
endmodule

siso_register/shift_reg_tb.v
`timescale 1ns/1ps

module shift_reg_tb;

    // Inputs
    reg in;
    reg clk;

    // Output
    wire out;

    // Instantiate SISO shift register
    shift_reg uut (
        .in(in),
        .clk(clk),
        .out(out)
    );

    // Clock generation
    always #5 clk = ~clk;

    initial begin

        // Waveform
        $dumpfile("shift_reg.vcd");
        $dumpvars(0, shift_reg_tb);

        // Monitor
        $monitor("Time=%0t | clk=%b | in=%b | out=%b",
                 $time, clk, in, out);

        // Initialize
        clk = 0;
        in = 0;

        // Send 1
        #2;
        in = 1;
        #10;

        // Send 0
        in = 0;
        #10;

        // Send 1
        in = 1;
        #10;

        // Send 1
        in = 1;
        #10;

        // Keep input low
        in = 0;
        #20;

        $finish;
    end

endmodule

siso_register/shift_reg.vcd
$date
	Tue Oct  6 06:04:06 2026
$end
$version
	Icarus Verilog
$end
$timescale
	1ps
$end
$scope module shift_reg_tb $end
$var wire 1 ! out $end
$var reg 1 " clk $end
$var reg 1 # in $end
$scope module uut $end
$var wire 1 " clk $end
$var wire 1 # in $end
$var wire 1 ! out $end
$var wire 1 $ m3 $end
$var wire 1 % m2 $end
$var wire 1 & m1 $end
$scope module dff0 $end
$var wire 1 " clk $end
$var wire 1 # d $end
$var reg 1 & q $end
$var reg 1 ' qbar $end
$upscope $end
$scope module dff1 $end
$var wire 1 " clk $end
$var wire 1 & d $end
$var reg 1 % q $end
$var reg 1 ( qbar $end
$upscope $end
$scope module dff2 $end
$var wire 1 " clk $end
$var wire 1 % d $end
$var reg 1 $ q $end
$var reg 1 ) qbar $end
$upscope $end
$scope module dff3 $end
$var wire 1 " clk $end
$var wire 1 $ d $end
$var reg 1 ! q $end
$var reg 1 * qbar $end
$upscope $end
$upscope $end
$upscope $end
$enddefinitions $end
#0
$dumpvars
x*
x)
x(
x'
x&
x%
x$
0#
0"
x!
$end
#2000
1#
#5000
0'
1&
1"
#10000
0"
#12000
0#
#15000
0(
1%
1'
0&
1"
#20000
0"
#22000
1#
#25000
0'
1&
1(
0%
0)
1$
1"
#30000
0"
#35000
0*
1!
1)
0$
0(
1%
1"
#40000
0"
#42000
0#
#45000
1'
0&
0)
1$
1*
0!
1"
#50000
0"
#55000
0*
1!
1(
0%
1"
