dmux4_1/dmux4_1.v
module dmux4_1(i, sel, y);
    input wire [3:0] i;
    input wire [1:0] sel;
    output wire y;

    assign y = (sel == 2'b00) ? i[0] :
               (sel == 2'b01) ? i[1] :
               (sel == 2'b10) ? i[2] :
               (sel == 2'b11) ? i[3] : 1'b0;

endmodule

dmux4_1/dmux4_1_tb.v
`timescale 1ns/1ps

module dmux4_1_tb;

    wire y;
    reg [1:0] sel;
    reg [3:0] i;

    // Instantiate DUT
    dmux4_1 uut (
        .i(i),
        .sel(sel),
        .y(y)
    );

    initial begin
        // Create waveform
        $dumpfile("dmux4_1.vcd");
        $dumpvars(0, dmux4_1_tb);

        // Display
        $monitor("Time=%0t | i=%b | sel=%b | y=%b",
                 $time, i, sel, y);

        // i = 0
        i = 4'b0000; sel = 2'b00; #10;
        i = 4'b0000; sel = 2'b01; #10;
        i = 4'b0000; sel = 2'b10; #10;
        i = 4'b0000; sel = 2'b11; #10;

        // i = 1
        i = 4'b0001; sel = 2'b00; #10;
        i = 4'b0001; sel = 2'b01; #10;
        i = 4'b0001; sel = 2'b10; #10;
        i = 4'b0001; sel = 2'b11; #10;

        $finish;
    end

endmodule

dmux4_1/dmux4_1.vcd
$date
	Sun Sep 27 10:35:03 2026
$end
$version
	Icarus Verilog
$end
$timescale
	1ps
$end
$scope module dmux4_1_tb $end
$var wire 1 ! y $end
$var reg 4 " i [3:0] $end
$var reg 2 # sel [1:0] $end
$scope module uut $end
$var wire 4 $ i [3:0] $end
$var wire 2 % sel [1:0] $end
$var wire 1 ! y $end
$upscope $end
$upscope $end
$enddefinitions $end
#0
$dumpvars
b0 %
b0 $
b0 #
b0 "
0!
$end
#10000
b1 #
b1 %
#20000
b10 #
b10 %
#30000
b11 #
b11 %
#40000
1!
b0 #
b0 %
b1 "
b1 $
#50000
0!
b1 #
b1 %
#60000
b10 #
b10 %
#70000
b11 #
b11 %
