SR_FF/SR_FF.v
module sr_ff (s, r, clk, q, qbar);
    input wire s, r, clk;
    output reg q, qbar;
    always@ (posedge clk) begin
      if (s == 0 && r == 0)
      begin
      q <= q;
      qbar <= qbar;
      end
      else if (s == 0 && r == 1)
      begin
      q <= 0;
      qbar <= 1;
      end
      else if (s == 1 && r == 0)
      begin
      q <= 1;
      qbar <= 0;
      end
      else if (s == 1 && r == 1)
      begin
        q <= 1'bx;
        qbar <= 1'bx;
      end
    end
endmodule

SR_FF/SR_FF_TB.v
`timescale 1ns/1ps

module sr_ff_tb;

    reg s, r, clk;
    wire q, qbar;

    integer i;

    sr_ff uut (
        .s(s),
        .r(r),
        .clk(clk),
        .q(q),
        .qbar(qbar)
    );

    // Clock
    always #5 clk = ~clk;

    initial begin
        $dumpfile("sr_ff_tb.vcd");
        $dumpvars(0, sr_ff_tb);

        clk = 0;
        s = 0;
        r = 0;

        $display("Time | CLK | S R | Q Qbar");
        $display("---------------------------");

        $monitor("%4t |  %b  | %b %b | %b   %b",
                 $time, clk, s, r, q, qbar);

        // 16 random S/R combinations
        for (i = 0; i < 16; i = i + 1) begin

            s = $random & 1'b1;
            r = $random & 1'b1;

            #10;

        end

        $finish;
    end

endmodule

SR_FF/sr_ff_tb.vcd
$date
	Wed Sep 23 14:06:45 2026
$end
$version
	Icarus Verilog
$end
$timescale
	1ps
$end
$scope module sr_ff_tb $end
$var wire 1 ! qbar $end
$var wire 1 " q $end
$var reg 1 # clk $end
$var reg 1 $ r $end
$var reg 1 % s $end
$var integer 32 & i [31:0] $end
$scope module uut $end
$var wire 1 # clk $end
$var wire 1 $ r $end
$var wire 1 % s $end
$var reg 1 " q $end
$var reg 1 ! qbar $end
$upscope $end
$upscope $end
$enddefinitions $end
#0
$dumpvars
b0 &
0%
1$
0#
x"
x!
$end
#5000
1!
0"
1#
#10000
0#
1%
b1 &
#15000
x!
x"
1#
#20000
0#
b10 &
#25000
1#
#30000
0#
0$
b11 &
#35000
0!
1"
1#
#40000
0#
1$
b100 &
#45000
x!
x"
1#
#50000
0#
0%
b101 &
#55000
1!
0"
1#
#60000
0#
0$
1%
b110 &
#65000
0!
1"
1#
#70000
0#
b111 &
#75000
1#
#80000
0#
b1000 &
#85000
1#
#90000
0#
1$
b1001 &
#95000
x!
x"
1#
#100000
0#
0%
b1010 &
#105000
1!
0"
1#
#110000
0#
0$
b1011 &
#115000
1#
#120000
0#
1$
b1100 &
#125000
1#
#130000
0#
b1101 &
#135000
1#
#140000
0#
1%
b1110 &
#145000
x!
x"
1#
#150000
0#
0$
b1111 &
#155000
0!
1"
1#
#160000
0#
b10000 &
