mux4_1/mux4_1.v
module mux4_1(
input I0,
input I1,
input I2,
input I3,
input wire [1:0] sel,
output reg y);

always @(*) begin
   case (sel)
        2'b00: y = I0;
        2'b01: y = I1;
        2'b10: y = I2;
        2'b11: y = I3;
  endcase
end
endmodule

Dff/Dff.v
module dff(d, clk, q, qbar);
    input wire d, clk;
    output reg q, qbar;

    always@(posedge clk) begin
        q <= d;
        qbar <= ~d;
    end
endmodule

4b_bidirec_reg/bidirec.v
module b4_bidirec_reg(in, clk, out, ctrl);
    input wire [3:0] in;
    input wire clk;
    input wire [1:0] ctrl;
    output wire [3:0] out;
wire m1, m2, m3, m4;
wire x2, x3;
assign x2 = 1'b0;
assign x3 = 1'b0;

dff dff0(.d(m1), .clk(clk), .q(out[0]), .qbar());
dff dff1(.d(m2), .clk(clk), .q(out[1]), .qbar());
dff dff2(.d(m3), .clk(clk), .q(out[2]), .qbar());
dff dff3(.d(m4), .clk(clk), .q(out[3]), .qbar());

mux4_1 mux0(.I0(in[0]), .I1(x2), .I2(out[1]), .I3(out[0]), .sel(ctrl), .y(m1));
mux4_1 mux1(.I0(in[1]), .I1(out[0]), .I2(out[2]), .I3(out[1]), .sel(ctrl), .y(m2));
mux4_1 mux2(.I0(in[2]), .I1(out[1]), .I2(out[3]), .I3(out[2]), .sel(ctrl), .y(m3));
mux4_1 mux3(.I0(in[3]), .I1(out[2]), .I2(x3), .I3(out[3]), .sel(ctrl), .y(m4));
endmodule

4b_bidirec_reg/bidirec_tb.v
`timescale 1ns/1ps

module bidirec_reg_tb;

    reg [3:0] in;
    reg clk;
    reg [1:0] ctrl;

    wire [3:0] out;

    integer i;

    // DUT
    b4_bidirec_reg uut (
        .in(in),
        .clk(clk),
        .out(out),
        .ctrl(ctrl)
    );

    // Clock
    always #5 clk = ~clk;

    initial begin

        // Waveform
        $dumpfile("bidirec_reg_tb.vcd");
        $dumpvars(0, bidirec_reg_tb);

        // Initial values
        clk = 0;
        in = 4'b0000;
        ctrl = 2'b11;

        $display("====================================================");
        $display("       4-BIT BIDIRECTIONAL REGISTER TEST");
        $display("====================================================");
        $display(" Time | CTRL |   IN   |   OUT  ");
        $display("----------------------------------------------------");

        $monitor("%4t  |  %02b  |  %04b   |  %04b",
                 $time, ctrl, in, out);

        // =================================================
        // TEST 1: PARALLEL LOAD
        // ctrl = 00
        // Test all 16 possible input combinations
        // =================================================

        ctrl = 2'b00;

        for (i = 0; i < 16; i = i + 1) begin
            in = i;
            #10;
        end


        // =================================================
        // TEST 2: SHIFT RIGHT
        // ctrl = 01
        // =================================================

        ctrl = 2'b01;
        in = 4'b0000;

        // Load starting value
        ctrl = 2'b00;
        in = 4'b1011;
        #10;

        // Shift right several times
        ctrl = 2'b01;

        #10;
        #10;
        #10;
        #10;
        #10;


        // =================================================
        // TEST 3: SHIFT RIGHT FROM DIFFERENT VALUES
        // =================================================

        ctrl = 2'b00;
        in = 4'b1111;
        #10;

        ctrl = 2'b01;
        #10;
        #10;
        #10;
        #10;


        ctrl = 2'b00;
        in = 4'b1001;
        #10;

        ctrl = 2'b01;
        #10;
        #10;
        #10;


        // =================================================
        // TEST 4: SHIFT LEFT
        // ctrl = 10
        // =================================================

        ctrl = 2'b00;
        in = 4'b1011;
        #10;

        ctrl = 2'b10;

        #10;
        #10;
        #10;
        #10;
        #10;


        // =================================================
        // TEST 5: SHIFT LEFT FROM DIFFERENT VALUES
        // =================================================

        ctrl = 2'b00;
        in = 4'b1111;
        #10;

        ctrl = 2'b10;

        #10;
        #10;
        #10;
        #10;


        ctrl = 2'b00;
        in = 4'b0101;
        #10;

        ctrl = 2'b10;

        #10;
        #10;
        #10;


        // =================================================
        // TEST 6: HOLD
        // ctrl = 11
        // =================================================

        ctrl = 2'b00;
        in = 4'b1100;
        #10;

        ctrl = 2'b11;

        // Change input but output should remain 1100
        in = 4'b0000;
        #10;

        in = 4'b1111;
        #10;

        in = 4'b0101;
        #10;

        in = 4'b0011;
        #10;


        // =================================================
        // TEST 7: MIXED OPERATIONS
        // =================================================

        // Load
        ctrl = 2'b00;
        in = 4'b1101;
        #10;

        // Right shift
        ctrl = 2'b01;
        #10;
        #10;

        // Hold
        ctrl = 2'b11;
        #10;
        #10;

        // Left shift
        ctrl = 2'b10;
        #10;
        #10;

        // Load another value
        ctrl = 2'b00;
        in = 4'b0110;
        #10;

        // Left shift
        ctrl = 2'b10;
        #10;
        #10;

        // Right shift
        ctrl = 2'b01;
        #10;
        #10;

        // Hold
        ctrl = 2'b11;
        #20;


        // =================================================
        // END
        // =================================================

        $display("====================================================");
        $display("                  TEST COMPLETE");
        $display("====================================================");

        $finish;

    end

endmodule

4b_bidirec_reg/bidirec_reg_tb.vcd
$date
	Thu Oct  8 06:03:23 2026
$end
$version
	Icarus Verilog
$end
$timescale
	1ps
$end
$scope module bidirec_reg_tb $end
$var wire 4 ! out [3:0] $end
$var reg 1 " clk $end
$var reg 2 # ctrl [1:0] $end
$var reg 4 $ in [3:0] $end
$var integer 32 % i [31:0] $end
$scope module uut $end
$var wire 1 " clk $end
$var wire 2 & ctrl [1:0] $end
$var wire 4 ' in [3:0] $end
$var wire 1 ( x2 $end
$var wire 1 ) x3 $end
$var wire 4 * out [3:0] $end
$var wire 1 + m4 $end
$var wire 1 , m3 $end
$var wire 1 - m2 $end
$var wire 1 . m1 $end
$scope module dff0 $end
$var wire 1 " clk $end
$var wire 1 . d $end
$var reg 1 / q $end
$var reg 1 0 qbar $end
$upscope $end
$scope module dff1 $end
$var wire 1 " clk $end
$var wire 1 - d $end
$var reg 1 1 q $end
$var reg 1 2 qbar $end
$upscope $end
$scope module dff2 $end
$var wire 1 " clk $end
$var wire 1 , d $end
$var reg 1 3 q $end
$var reg 1 4 qbar $end
$upscope $end
$scope module dff3 $end
$var wire 1 " clk $end
$var wire 1 + d $end
$var reg 1 5 q $end
$var reg 1 6 qbar $end
$upscope $end
$scope module mux0 $end
$var wire 1 7 I0 $end
$var wire 1 ( I1 $end
$var wire 1 8 I2 $end
$var wire 1 9 I3 $end
$var wire 2 : sel [1:0] $end
$var reg 1 . y $end
$upscope $end
$scope module mux1 $end
$var wire 1 ; I0 $end
$var wire 1 < I1 $end
$var wire 1 = I2 $end
$var wire 1 > I3 $end
$var wire 2 ? sel [1:0] $end
$var reg 1 - y $end
$upscope $end
$scope module mux2 $end
$var wire 1 @ I0 $end
$var wire 1 A I1 $end
$var wire 1 B I2 $end
$var wire 1 C I3 $end
$var wire 2 D sel [1:0] $end
$var reg 1 , y $end
$upscope $end
$scope module mux3 $end
$var wire 1 E I0 $end
$var wire 1 F I1 $end
$var wire 1 ) I2 $end
$var wire 1 G I3 $end
$var wire 2 H sel [1:0] $end
$var reg 1 + y $end
$upscope $end
$upscope $end
$upscope $end
$enddefinitions $end
#0
$dumpvars
b0 H
xG
xF
0E
b0 D
xC
xB
xA
0@
b0 ?
x>
x=
x<
0;
b0 :
x9
x8
07
x6
x5
x4
x3
x2
x1
x0
x/
0.
0-
0,
0+
bx *
0)
0(
b0 '
b0 &
b0 %
b0 $
b0 #
0"
bx !
$end
#5000
09
0<
08
0>
0A
0=
0C
0F
0B
0G
10
0/
12
01
14
03
16
b0 !
b0 *
05
1"
#10000
1.
17
0"
b1 $
b1 '
b1 %
#15000
19
1<
00
b1 !
b1 *
1/
1"
#20000
0.
1-
07
1;
0"
b10 $
b10 '
b10 %
#25000
09
0<
18
1>
1A
10
0/
02
b10 !
b10 *
11
1"
#30000
1.
17
0"
b11 $
b11 '
b11 %
#35000
19
1<
00
b11 !
b11 *
1/
1"
#40000
0.
0-
1,
07
0;
1@
0"
b100 $
b100 '
b100 %
#45000
09
0<
08
0>
0A
1=
1C
1F
10
0/
12
01
04
b100 !
b100 *
13
1"
#50000
1.
17
0"
b101 $
b101 '
b101 %
#55000
19
1<
00
b101 !
b101 *
1/
1"
#60000
0.
1-
07
1;
0"
b110 $
b110 '
b110 %
#65000
09
0<
18
1>
1A
10
0/
02
b110 !
b110 *
11
1"
#70000
1.
17
0"
b111 $
b111 '
b111 %
#75000
19
1<
00
b111 !
b111 *
1/
1"
#80000
0.
0-
0,
1+
07
0;
0@
1E
0"
b1000 $
b1000 '
b1000 %
#85000
09
0<
08
0>
0A
0=
0C
0F
1B
1G
10
0/
12
01
14
03
06
b1000 !
b1000 *
15
1"
#90000
1.
17
0"
b1001 $
b1001 '
b1001 %
#95000
19
1<
00
b1001 !
b1001 *
1/
1"
#100000
0.
1-
07
1;
0"
b1010 $
b1010 '
b1010 %
#105000
09
0<
18
1>
1A
10
0/
02
b1010 !
b1010 *
11
1"
#110000
1.
17
0"
b1011 $
b1011 '
b1011 %
#115000
19
1<
00
b1011 !
b1011 *
1/
1"
#120000
0.
0-
1,
07
0;
1@
0"
b1100 $
b1100 '
b1100 %
#125000
09
0<
08
0>
0A
1=
1C
1F
10
0/
12
01
04
b1100 !
b1100 *
13
1"
#130000
1.
17
0"
b1101 $
b1101 '
b1101 %
#135000
19
1<
00
b1101 !
b1101 *
1/
1"
#140000
0.
1-
07
1;
0"
b1110 $
b1110 '
b1110 %
#145000
09
0<
18
1>
1A
10
0/
02
b1110 !
b1110 *
11
1"
#150000
1.
17
0"
b1111 $
b1111 '
b1111 %
#155000
19
1<
00
b1111 !
b1111 *
1/
1"
#160000
0,
0@
0"
b1011 $
b1011 '
b0 #
b0 &
b0 :
b0 ?
b0 D
b0 H
b10000 %
#165000
0=
0C
0F
14
b1011 !
b1011 *
03
1"
#170000
0.
1,
0+
0"
b1 #
b1 &
b1 :
b1 ?
b1 D
b1 H
#175000
1+
0-
0B
0G
1=
1C
1F
09
0<
16
05
04
13
10
b110 !
b110 *
0/
1"
#180000
0"
#185000
0,
08
0>
0A
1B
1G
12
01
06
b1100 !
b1100 *
15
1"
#190000
0"
#195000
0+
0=
0C
0F
14
b1000 !
b1000 *
03
1"
#200000
0"
#205000
0B
0G
16
b0 !
b0 *
05
1"
#210000
0"
#215000
1"
#220000
1,
1@
1.
1-
1+
0"
b1111 $
b1111 '
b0 #
b0 &
b0 :
b0 ?
b0 D
b0 H
#225000
19
1<
18
1>
1A
1=
1C
1F
1B
1G
00
1/
02
11
04
13
06
b1111 !
b1111 *
15
1"
#230000
0.
0"
b1 #
b1 &
b1 :
b1 ?
b1 D
b1 H
#235000
0-
09
0<
10
b1110 !
b1110 *
0/
1"
#240000
0"
#245000
0,
08
0>
0A
12
b1100 !
b1100 *
01
1"
#250000
0"
#255000
0+
0=
0C
0F
14
b1000 !
b1000 *
03
1"
#260000
0"
#265000
0B
0G
16
b0 !
b0 *
05
1"
#270000
0;
0@
1.
0-
0,
1+
0"
b1001 $
b1001 '
b0 #
b0 &
b0 :
b0 ?
b0 D
b0 H
#275000
1B
1G
19
1<
06
15
00
b1001 !
b1001 *
1/
1"
#280000
0.
1-
0+
0"
b1 #
b1 &
b1 :
b1 ?
b1 D
b1 H
#285000
0-
1,
09
0<
18
1>
1A
0B
0G
10
0/
02
11
16
b10 !
b10 *
05
1"
#290000
0"
#295000
1+
0,
1=
1C
1F
08
0>
0A
04
13
12
b100 !
b100 *
01
1"
#300000
0"
#305000
0+
0=
0C
0F
1B
1G
14
03
06
b1000 !
b1000 *
15
1"
#310000
1-
1;
1.
1+
0"
b1011 $
b1011 '
b0 #
b0 &
b0 :
b0 ?
b0 D
b0 H
#315000
18
1>
1A
19
1<
02
11
00
b1011 !
b1011 *
1/
1"
#320000
0-
1,
0+
0"
b10 #
b10 &
b10 :
b10 ?
b10 D
b10 H
#325000
0.
1-
0,
08
0>
0A
1=
1C
1F
0B
0G
12
01
04
13
16
b101 !
b101 *
05
1"
#330000
0"
#335000
1.
0-
0=
0C
0F
18
1>
1A
09
0<
14
03
02
11
10
b10 !
b10 *
0/
1"
#340000
0"
#345000
0.
19
1<
08
0>
0A
00
1/
12
b1 !
b1 *
01
1"
#350000
0"
#355000
09
0<
10
b0 !
b0 *
0/
1"
#360000
0"
#365000
1"
#370000
1,
1@
1.
1-
1+
0"
b1111 $
b1111 '
b0 #
b0 &
b0 :
b0 ?
b0 D
b0 H
#375000
1B
1G
1=
1C
1F
18
1>
1A
19
1<
06
15
04
13
02
11
00
b1111 !
b1111 *
1/
1"
#380000
0+
0"
b10 #
b10 &
b10 :
b10 ?
b10 D
b10 H
#385000
0,
0B
0G
16
b111 !
b111 *
05
1"
#390000
0"
#395000
0-
0=
0C
0F
14
b11 !
b11 *
03
1"
#400000
0"
#405000
0.
08
0>
0A
12
b1 !
b1 *
01
1"
#410000
0"
#415000
09
0<
10
b0 !
b0 *
0/
1"
#420000
0;
0E
1.
0-
1,
0+
0"
b101 $
b101 '
b0 #
b0 &
b0 :
b0 ?
b0 D
b0 H
#425000
19
1<
1=
1C
1F
00
1/
04
b101 !
b101 *
13
1"
#430000
0.
1-
0,
0"
b10 #
b10 &
b10 :
b10 ?
b10 D
b10 H
#435000
1.
0-
0=
0C
0F
18
1>
1A
09
0<
14
03
02
11
10
b10 !
b10 *
0/
1"
#440000
0"
#445000
0.
19
1<
08
0>
0A
00
1/
12
b1 !
b1 *
01
1"
#450000
0"
#455000
09
0<
10
b0 !
b0 *
0/
1"
#460000
1+
07
1E
0.
1,
0"
b1100 $
b1100 '
b0 #
b0 &
b0 :
b0 ?
b0 D
b0 H
#465000
1=
1C
1F
1B
1G
04
13
06
b1100 !
b1100 *
15
1"
#470000
0@
0E
0"
b0 $
b0 '
b11 #
b11 &
b11 :
b11 ?
b11 D
b11 H
#475000
1"
#480000
17
1;
1@
1E
0"
b1111 $
b1111 '
#485000
1"
#490000
0;
0E
0"
b101 $
b101 '
#495000
1"
#500000
1;
0@
0"
b11 $
b11 '
#505000
1"
#510000
0;
1@
1E
1.
0-
1,
1+
0"
b1101 $
b1101 '
b0 #
b0 &
b0 :
b0 ?
b0 D
b0 H
#515000
19
1<
00
b1101 !
b1101 *
1/
1"
#520000
0.
1-
0,
0"
b1 #
b1 &
b1 :
b1 ?
b1 D
b1 H
#525000
0-
1,
0+
09
0<
18
1>
1A
0=
0C
0F
10
0/
02
11
14
b1010 !
b1010 *
03
1"
#530000
0"
#535000
1+
0,
0B
0G
1=
1C
1F
08
0>
0A
16
05
04
13
12
b100 !
b100 *
01
1"
#540000
1,
0+
0"
b11 #
b11 &
b11 :
b11 ?
b11 D
b11 H
#545000
1"
#550000
0"
#555000
1"
#560000
1-
0,
0"
b10 #
b10 &
b10 :
b10 ?
b10 D
b10 H
#565000
1.
0-
18
1>
1A
0=
0C
0F
02
11
14
b10 !
b10 *
03
1"
#570000
0"
#575000
0.
08
0>
0A
19
1<
12
01
00
b1 !
b1 *
1/
1"
#580000
1-
07
1;
0E
0.
1,
0+
0"
b110 $
b110 '
b0 #
b0 &
b0 :
b0 ?
b0 D
b0 H
#585000
09
0<
18
1>
1A
1=
1C
1F
10
0/
02
11
04
b110 !
b110 *
13
1"
#590000
1.
0,
0"
b10 #
b10 &
b10 :
b10 ?
b10 D
b10 H
#595000
0-
0=
0C
0F
19
1<
14
03
00
b11 !
b11 *
1/
1"
#600000
0"
#605000
0.
08
0>
0A
12
b1 !
b1 *
01
1"
#610000
1-
0"
b1 #
b1 &
b1 :
b1 ?
b1 D
b1 H
#615000
1,
0-
18
1>
1A
09
0<
02
11
10
b10 !
b10 *
0/
1"
#620000
0"
#625000
0,
1+
08
0>
0A
1=
1C
1F
12
01
04
b100 !
b100 *
13
1"
#630000
1,
0+
0"
b11 #
b11 &
b11 :
b11 ?
b11 D
b11 H
