carry_LA4/carry_LA.v
module CLA_4 (
    input [3:0] A,
    input [3:0] B,
    input Cin,
    output [3:0] S,
    output Cout
);
wire [3:0] p,g;
wire [4:0] c;
assign c[0] = Cin;

assign p = A ^ B; // Propogate
assign g = A & B; // Generate

// Carry Lookahead Logic
assign c[1] = g[0] | (p[0] & Cin);
assign c[2] = g[1] | (p[1] & g[0]) | (p[1] & p[0] & Cin);
assign c[3] = g[2] | (p[2] & g[1]) | (p[2] & p[1] & g[0]) | (p[2] & p[1] & p[0] & Cin);
assign c[4] = g[3] | (p[3] & g[2]) | (p[3] & p[2] & g[1]) | (p[3] & p[2] & p[1] & g[0]) | (p[3] & p[2] & p[1] & p[0] & Cin);

// Sum Calculation
assign S[0] = p[0] ^ c[0];
assign S[1] = p[1] ^ c[1];
assign S[2] = p[2] ^ c[2];
assign S[3] = p[3] ^ c[3];
assign Cout = c[4];
endmodule

carry_LA4/carry_LA_tb.v
`timescale 1ns/1ps

module CLA_4_tb;

    reg  [3:0] A;
    reg  [3:0] B;
    reg        Cin;

    wire [3:0] S;
    wire       Cout;

    reg [4:0] expected;

    integer i;

    // Instantiate CLA
    CLA_4 uut (
        .A(A),
        .B(B),
        .Cin(Cin),
        .S(S),
        .Cout(Cout)
    );

    initial begin

        $dumpfile("CLA_4.vcd");
        $dumpvars(0, CLA_4_tb);

        $display("------------------------------------------------");
        $display(" A     B    Cin |  S    Cout | Expected | Result");
        $display("------------------------------------------------");

        for (i = 0; i < 10; i = i + 1) begin

            // Generate random 4-bit numbers
            A   = $random & 4'b1111;
            B   = $random & 4'b1111;
            Cin = $random & 1'b1;

            #10;

            // Calculate expected result
            expected = A + B + Cin;

            // Check CLA output
            if ({Cout, S} !== expected) begin
                $display("%b  %b    %b  | %b    %b   |  %b    | FAIL",
                         A, B, Cin, S, Cout, expected);
            end
            else begin
                $display("%b  %b    %b  | %b    %b   |  %b    | PASS",
                         A, B, Cin, S, Cout, expected);
            end

        end

        $display("------------------------------------------------");

        $finish;
    end

endmodule

carry_LA4/CLA_4.vcd
$date
	Tue Sep  8 06:17:58 2026
$end
$version
	Icarus Verilog
$end
$timescale
	1ps
$end
$scope module CLA_4_tb $end
$var wire 4 ! S [3:0] $end
$var wire 1 " Cout $end
$var reg 4 # A [3:0] $end
$var reg 4 $ B [3:0] $end
$var reg 1 % Cin $end
$var reg 5 & expected [4:0] $end
$var integer 32 ' i [31:0] $end
$scope module uut $end
$var wire 4 ( A [3:0] $end
$var wire 4 ) B [3:0] $end
$var wire 1 % Cin $end
$var wire 4 * g [3:0] $end
$var wire 4 + p [3:0] $end
$var wire 5 , c [4:0] $end
$var wire 4 - S [3:0] $end
$var wire 1 " Cout $end
$upscope $end
$upscope $end
$enddefinitions $end
#0
$dumpvars
b110 -
b11 ,
b101 +
b0 *
b1 )
b100 (
b0 '
bx &
1%
b1 $
b100 #
0"
b110 !
$end
#10000
1"
b11111 ,
b1 !
b1 -
b1110 +
b1 *
b1101 $
b1101 )
b11 #
b11 (
b1 '
b110 &
#20000
0"
b1000 !
b1000 -
b1111 ,
b111 +
b0 *
b10 $
b10 )
b101 #
b101 (
b10 '
b10001 &
#30000
1"
b11111 ,
b100 !
b100 -
b1011 +
b100 *
b110 $
b110 )
b1101 #
b1101 (
b11 '
b1000 &
#40000
b11011 ,
b1010 !
b1010 -
b1 +
b1100 *
b1100 $
b1100 )
b100 '
b10100 &
#50000
0"
b1011 !
b1011 -
b11 +
b100 *
b1000 ,
0%
b101 $
b101 )
b110 #
b110 (
b101 '
b11010 &
#60000
b1100 !
b1100 -
b1110 ,
b10 +
b101 *
b111 $
b111 )
b101 #
b101 (
b110 '
b1011 &
#70000
1"
b1 !
b1 -
b11100 ,
b1101 +
b10 *
b10 $
b10 )
b1111 #
b1111 (
b111 '
b1100 &
#80000
0"
b1101 !
b1101 -
b0 ,
b0 *
b101 $
b101 )
b1000 #
b1000 (
b1000 '
b10001 &
#90000
1"
b1011 !
b1011 -
b0 +
b1101 *
b11011 ,
1%
b1101 $
b1101 )
b1101 #
b1101 (
b1001 '
b1101 &
#100000
b1010 '
b11011 &
